AMON/__init__.py
AMON/amon.py
AMON/extract_ko_genome_from_organism.py
AMON/get_kegg_files.py
AMON/predict_metabolites.py
amon_bio-1.1.0.dist-info/licenses/LICENSE
tests/test_predict_metabolites.py
amon_bio-1.1.0.dist-info/METADATA
amon_bio-1.1.0.dist-info/WHEEL
amon_bio-1.1.0.dist-info/entry_points.txt
amon_bio-1.1.0.dist-info/top_level.txt
amon_bio-1.1.0.dist-info/RECORD
