Metadata-Version: 2.4
Name: AMON-bio
Version: 1.1.0
Summary: Annotation of Metabolite Origin via Networks: A tool for predicting putative
Author: Kumar Thurimella
Author-email: Michael Shaffer <lozuponelab.dev@olucdenver.onmicrosoft.com>
License: MIT
Project-URL: Homepage, https://github.com/lozuponelab/AMON/
Project-URL: Download, https://github.com/lozuponelab/AMON/tarball
License-File: LICENSE
Requires-Dist: scipy
Requires-Dist: biom-format
Requires-Dist: pandas
Requires-Dist: matplotlib
Requires-Dist: statsmodels
Requires-Dist: numpy
Requires-Dist: aiohttp
Requires-Dist: seaborn
Requires-Dist: matplotlib-venn
Requires-Dist: KEGG-parser
Dynamic: license-file
